pdf_tools_sdk_test/__init__.py
pdf_tools_sdk_test/py_ctypes.py
pdf_tools_sdk_test/streams.py
pdf_tools_sdk_test/utils.py
pdf_tools_sdk_test/lib/linux-x64/libPdfToolsSdk.so
pdf_tools_sdk_test/lib/osx-arm64/libPdfToolsSdk.dylib
pdf_tools_sdk_test/lib/osx-x64/libPdfToolsSdk.dylib
pdf_tools_sdk_test/lib/win-x64/PdfToolsSdk.dll
pdf_tools_sdk_test/lib/win-x86/PdfToolsSdk.dll
pdf_tools_sdk_test-0.1.0.dist-info/METADATA
pdf_tools_sdk_test-0.1.0.dist-info/WHEEL
pdf_tools_sdk_test-0.1.0.dist-info/top_level.txt
pdf_tools_sdk_test-0.1.0.dist-info/RECORD
