Metadata-Version: 2.1
Name: pdf_tools_sdk_test
Version: 0.1.0
Summary: Python package for Pdftools SDK
